{
  "kind": "Root",
  "name": "TopLevel",
  "printedName": "TopLevel",
  "children": [
    {
      "kind": "Function",
      "name": "f",
      "printedName": "f()",
      "children": [
        {
          "kind": "TypeNominal",
          "name": "Void",
          "printedName": "()"
        }
      ],
      "declKind": "Func",
      "usr": "s:6Simple1fyyF",
      "mangledName": "$s6Simple1fyyF",
      "moduleName": "Simple",
      "funcSelfKind": "NonMutating"
    },
    {
      "kind": "Function",
      "name": "g",
      "printedName": "g(_:)",
      "children": [
        {
          "kind": "TypeNominal",
          "name": "Void",
          "printedName": "()"
        },
        {
          "kind": "TypeNominal",
          "name": "Int",
          "printedName": "Swift.Int",
          "usr": "s:Si"
        }
      ],
      "declKind": "Func",
      "usr": "s:6Simple1gyySiF",
      "mangledName": "$s6Simple1gyySiF",
      "moduleName": "Simple",
      "funcSelfKind": "NonMutating"
    },
    {
      "kind": "Function",
      "name": "countdown",
      "printedName": "countdown(_:)",
      "children": [
        {
          "kind": "TypeNominal",
          "name": "Void",
          "printedName": "()"
        },
        {
          "kind": "TypeNominal",
          "name": "Int",
          "printedName": "Swift.Int",
          "usr": "s:Si"
        }
      ],
      "declKind": "Func",
      "usr": "s:6Simple9countdownyySiF",
      "mangledName": "$s6Simple9countdownyySiF",
      "moduleName": "Simple",
      "funcSelfKind": "NonMutating"
    }
  ],
  "json_format_version": 6
}